{
  "$schema": "https://json-schema.org/draft/2020-12/schema",
  "$id": "https://example.com/read_options_csv.schema.json",
  "title": "Delimited Text Dataset",
  "description": "An delimited text format described by a flat file format. CSV is a misnomer however it's consistent with spark",
  "type": "object",
  "properties": {
    "timestamp_format": {
      "type": "string"
    },
    "date_format": {
      "type": "string"
    }
  },
  "required": [
    "timestamp_format",
    "date_format"
  ]
}
